amdgpu_stats/__init__.py
amdgpu_stats/__main__.py
amdgpu_stats/style.css
amdgpu_stats/tui.py
amdgpu_stats/utils.py
amdgpu_stats-0.1.24.dist-info/LICENSE.md
amdgpu_stats-0.1.24.dist-info/METADATA
amdgpu_stats-0.1.24.dist-info/WHEEL
amdgpu_stats-0.1.24.dist-info/entry_points.txt
amdgpu_stats-0.1.24.dist-info/RECORD
