Metadata-Version: 2.1
Name: amdgpu-stats
Version: 0.1.24
Summary: A module/TUI for AMD GPU statistics
Home-page: https://github.com/joshlay/amdgpu_stats
License: MIT
Author: Josh Lay
Author-email: pypi@jlay.io
Requires-Python: >=3.8,<4.0
Classifier: Environment :: Console
Classifier: Environment :: GPU
Classifier: Intended Audience :: Developers
Classifier: Intended Audience :: End Users/Desktop
Classifier: Intended Audience :: System Administrators
Classifier: License :: OSI Approved :: MIT License
Classifier: Operating System :: POSIX :: Linux
Classifier: Programming Language :: Python :: 3
Classifier: Programming Language :: Python :: 3.8
Classifier: Programming Language :: Python :: 3.9
Classifier: Programming Language :: Python :: 3.10
Classifier: Programming Language :: Python :: 3.11
Classifier: Programming Language :: Python :: 3.12
Requires-Dist: humanfriendly (>=10.0)
Requires-Dist: textual (>=0.32.0)
Project-URL: Documentation, https://amdgpu-stats.readthedocs.io/en/latest/
Project-URL: Repository, https://github.com/joshlay/amdgpu_stats
